fugue_anyscale/__init__.py
fugue_anyscale/cluster.py
fugue_anyscale/execution_engine.py
fugue_anyscale/registry.py
fugue_aws/__init__.py
fugue_aws/_instances_data.py
fugue_aws/instance_utils.py
fugue_cloudprovider/__init__.py
fugue_cloudprovider_version/__init__.py
fugue_coiled/__init__.py
fugue_coiled/client.py
fugue_coiled/registry.py
fugue_databricks/__init__.py
fugue_databricks/_utils.py
fugue_databricks/exceptions.py
fugue_databricks/execution_engine.py
fugue_databricks/registry.py
fugue_cloudprovider-0.2.0.dist-info/LICENSE
fugue_cloudprovider-0.2.0.dist-info/METADATA
fugue_cloudprovider-0.2.0.dist-info/WHEEL
fugue_cloudprovider-0.2.0.dist-info/entry_points.txt
fugue_cloudprovider-0.2.0.dist-info/top_level.txt
fugue_cloudprovider-0.2.0.dist-info/RECORD
